[
 {
  "name": "СОМ на Кунавина",
  "address": "г. Богданович, ул. Кунавина 100",
  "phone_number": "8 (800) 2500-900 доб. 809, +7 (902) 2778888",
  "working_hours": "Пн – Вс: 08:00 – 20:00"
 },
 {
  "name": "СОМ на Попова",
  "address": "г. Заречный, ул. Попова 1а",
  "phone_number": "8 (800) 2500-900 доб. 811, +7 (982) 6903463",
  "working_hours": "Пн – Сб: 08:00 – 20:00, Вс: 08:00 – 19:00"
 },
 {
  "name": "СОМ на Карла Маркса",
  "address": "г. Верхняя Салда, ул. Карла Маркса, 22",
  "phone_number": "8 (800) 2500-900 доб. 808, +7 (912) 6903699",
  "working_hours": "Пн – Сб: 08:00 – 20:00, Вс: 08:00 – 19:00"
 },
 {
  "name": "СОМ на 4 Пятилетке",
  "address": "г. Каменск-Уральский, ул. 4 Пятилетки, 47",
  "phone_number": "8 (800) 2500-900 доб. 804, +7 (912) 6903571",
  "working_hours": "Пн – Сб: 08:00 – 20:00, Вс: 08:00 – 19:00"
 },
 {
  "name": "СОМ на Тургенева",
  "address": "г. Качканар, Тургенева 1/24",
  "phone_number": "8 (800) 2500-900 доб. 812",
  "working_hours": "Пн – Вс: 08:00 – 20:00"
 },
 {
  "name": "СОМ на Валентины Терешковой",
  "address": "г. Красноуфимск, Валентины Терешковой 96 А",
  "phone_number": "8 (800) 2500-900 доб. 815, +7 (912) 2406280",
  "working_hours": "Пн – Пт: 08:00 – 20:00, Вс: 08:00 – 19:00"
 },
 {
  "name": "СОМ на Кирова",
  "address": "г. Невьянск, ул. Кирова 38",
  "phone_number": "8 (800) 2500-900 доб. 824, +7 (912) 270-03-16",
  "working_hours": "Пн – Вс: 08:00 – 20:00"
 },
 {
  "name": "СОМ на Красноармейской",
  "address": "г. Нижний Тагил, Красноармейская, 79К ",
  "phone_number": "8 (800) 2500-900 доб. 810, +7 (982) 6903887",
  "working_hours": "Пн-Вс с 08:00 до 21:00"
 },
 {
  "name": "СОМ на Малышева",
  "address": "г. Нижняя Тура, ул. Малышева 2А",
  "phone_number": "8 (800) 2500-900 доб. 814, +7 (982) 6706395",
  "working_hours": "Пн - Сб: 08:00 – 20:00, Вс: 8:00 – 19:00"
 },
 {
  "name": "СОМ на Автозаводской",
  "address": "г. Новоуральск, ул. Автозаводская, 21",
  "phone_number": "8 (800) 2500-900 доб. 807, +7 (912) 6904094",
  "working_hours": "Пн – Сб: 08:00 – 20:00, Вс: 08:00 -19:00"
 },
 {
  "name": "СОМ на Ленина",
  "address": "г. Первоуральск, ул. Ленина, 41",
  "phone_number": "+7-902-266-06-06",
  "working_hours": "Пн – Сб: 09:00 – 21:00, Вс: 09:00 – 20:00"
 },
 {
  "name": "СОМ на Совхозной",
  "address": "г. Полевской, Совхозная 18",
  "phone_number": "8 (800) 2500-900 доб. 820, +7 (912) 2700844",
  "working_hours": "Ежедневно 08:00-20:00"
 },
 {
  "name": "СОМ на Горького",
  "address": "г. Ревда, ул. Горького, 48",
  "phone_number": "8 (800) 2500-900 доб. 803, +7 (912) 6903817",
  "working_hours": "Пн – Сб: 08:30 – 20:00, Вс: 08:30 – 19:00"
 },
 {
  "name": "СОМ на Интернациональной",
  "address": "г. Нижневартовск, Интернациональная, 38А",
  "phone_number": "8 (800) 2500-900 доб. 816, +7 (982) 6602601",
  "working_hours": "Пн-Сб с 08:00 до 21:00, Вс с 08:00 до 20:00"
 },
 {
  "name": "СОМ на Сергинской",
  "address": "г. Нягань, ул. Сергинская 20, корпус 2",
  "phone_number": "8 (800) 2500-900 доб. 818, +7 (912) 2405490",
  "working_hours": "Пн - Сб: 08:00 – 20:00, Вс: 08:00 – 19:00"
 },
 {
  "name": "СОМ на Сургутской",
  "address": "г. Нефтеюганск, ул. Сургутская 18/11",
  "phone_number": "8 (800) 2500-900 доб. 819, +7 (982) 6609630",
  "working_hours": "Ежедневно с 08:00 до 20:00"
 },
 {
  "name": "СОМ на Сутормина",
  "address": "г. Ханты-Мансийск, Сутормина 20",
  "phone_number": "8 (800) 2500-900 доб. 822, +7 912 690-46-80",
  "working_hours": "Пн-Сб с 08:00 до 20:00, Вск с 08:00 до 19:00"
 },
 {
  "name": "СОМ на Рощинском",
  "address": "г. Тобольск, Рощинский переулок, 68В/2",
  "phone_number": "8 (800) 2500-900 доб. 817, +7 (982) 7001626",
  "working_hours": "Пн - Вс: 08:00 – 21:00"
 },
 {
  "name": "СОМ на Котлостроительной",
  "address": "г. Таганрог, ул.Котлостроительная, 37/15",
  "phone_number": "8 (800) 2500-900 доб. 821, +7 (912) 2301458",
  "working_hours": "Пн - Вс: 08:00 – 21:00"
 },
 {
  "name": "СОМ на Герцена",
  "address": "г. Ейск, ул. Герцена, д. 9",
  "phone_number": "8 (800) 2500-900 доб. 823",
  "working_hours": "Пн - Вс: 08:00 – 20:00"
 },
 {
  "name": "СОМ на Котанова",
  "address": "г. Новороссийск, ул. Котанова, д. 3",
  "phone_number": "8 (800) 2500-900 доб. 826, +7 (912) 200-07-98",
  "working_hours": "Пн - Вс: 08:00 – 21:00"
 },
 {
  "name": "СОМ на Украинской",
  "address": "г. Михайловка, Украинская, 74",
  "phone_number": "8 (800) 2500-900 доб. 825, + 7 (982) 690-06-14",
  "working_hours": "Пн – Вс: 08:00 – 20:00"
 }
]